peblo/__init__.py
peblo/__main__.py
peblo/cli/__init__.py
peblo/cli/loggings.py
peblo/cli/main.py
peblo/cli/chat/__init__.py
peblo/cli/chat/session.py
peblo/commons/__init__.py
peblo/commons/culture.py
peblo/commons/text.py
peblo/commons/io/__init__.py
peblo/commons/io/files.py
peblo/commons/io/images.py
peblo/commons/io/pdf.py
peblo/commons/io/web.py
peblo/commons/llm/__init__.py
peblo/commons/llm/postprocess.py
peblo/commons/llm/preprocess.py
peblo/commons/llm/tokenizers.py
peblo/config/__init__.py
peblo/config/global_config.py
peblo/config/models.py
peblo/prompts/__init__.py
peblo/providers/__init__.py
peblo/providers/base.py
peblo/providers/deepseek.py
peblo/providers/ollama.py
peblo/providers/openrouter.py
peblo/providers/qwen.py
peblo/providers/registry.py
peblo/schemas/__init__.py
peblo/schemas/chat.py
peblo/schemas/models.py
peblo/scripts/__init__.py
peblo/scripts/parse_jds.py
peblo/tools/__init__.py
peblo/tools/general.py
peblo/tools/image.py
peblo/tools/ocr.py
peblo/tools/peek.py
peblo/tools/qa.py
peblo/tools/quote.py
peblo/tools/summarize.py
peblo/tools/text_input.py
peblo/tools/translate.py
peblo-0.0.3.dist-info/licenses/LICENSE
peblo-0.0.3.dist-info/METADATA
peblo-0.0.3.dist-info/WHEEL
peblo-0.0.3.dist-info/entry_points.txt
peblo-0.0.3.dist-info/top_level.txt
peblo-0.0.3.dist-info/RECORD
